tile_mate/__init__.py
tile_mate/exceptions.py
tile_mate/stitcher.py
tile_mate/tile_model.py
tile_mate/data/asf_hand_2021.geojson.zip
tile_mate/data/cop_100m_lulc_discrete_classes.geojson.zip
tile_mate/data/esa_world_cover_2020.geojson.zip
tile_mate/data/esa_world_cover_2021.geojson.zip
tile_mate/data/glad_landcover_2020.geojson.zip
tile_mate/data/hansen_landsat_mosaic_2022.geojson.zip
tile_mate/data/pekel_water_occurrence_2021.geojson.zip
tile_mate/data/radd_deforestation_alerts_2022.geojson.zip
tile_mate/data/s1_coherence_2020.geojson.zip
tile_mate/data/umd_ocean_mask.geojson.zip
tile_mate-0.0.15.dist-info/licenses/LICENSE.txt
tile_mate-0.0.15.dist-info/METADATA
tile_mate-0.0.15.dist-info/WHEEL
tile_mate-0.0.15.dist-info/top_level.txt
tile_mate-0.0.15.dist-info/RECORD
