Metadata-Version: 2.4
Name: tile-mate
Version: 0.0.15
Summary: Create rasters from global tiles
Author: Alexander Handwerger, Charlie Marshak, and OPERA Project Science Team
License: Apache-2.0
Project-URL: Homepage, https://github.com/OPERA-Cal-Val/tile-mate
Project-URL: Bug Tracker, https://github.com/OPERA-Cal-Val/tile-mate/issues
Classifier: Intended Audience :: Science/Research
Classifier: Natural Language :: English
Classifier: Operating System :: OS Independent
Classifier: Programming Language :: Python :: 3
Classifier: Programming Language :: Python :: 3.9
Classifier: Programming Language :: Python :: 3.10
Classifier: Programming Language :: Python :: 3.11
Classifier: Programming Language :: Python :: 3.12
Classifier: Programming Language :: Python :: 3.13
Requires-Python: >=3.9
License-File: LICENSE.txt
Requires-Dist: boto3
Requires-Dist: rasterio
Requires-Dist: tqdm
Requires-Dist: geopandas
Requires-Dist: matplotlib
Requires-Dist: numpy
Requires-Dist: pandas
Requires-Dist: pandera
Requires-Dist: shapely
Requires-Dist: dem-stitcher>=2.5.4
Provides-Extra: develop
Requires-Dist: pytest; extra == "develop"
Requires-Dist: pytest-cov; extra == "develop"
Requires-Dist: flake8; extra == "develop"
Requires-Dist: flake8-import-order; extra == "develop"
Requires-Dist: flake8-blind-except; extra == "develop"
Requires-Dist: flake8-builtins; extra == "develop"
Dynamic: license-file
